idem_azure_auto/conf.py
idem_azure_auto/version.py
idem_azure_auto/acct/azure/login.py
idem_azure_auto/acct/azure/mock.py
idem_azure_auto/acct/metadata/azure.py
idem_azure_auto/backup/storage_resource_provider/storage_accounts.py
idem_azure_auto/backup/virtual_networks/nat_gateways.py
idem_azure_auto/backup/virtual_networks/public_ip_addresses.py
idem_azure_auto/backup/virtual_networks/routes.py
idem_azure_auto/backup/virtual_networks/security_rules.py
idem_azure_auto/exec/azure/init.py
idem_azure_auto/exec/azure/permission.py
idem_azure_auto/exec/azure/authorization/role_assignments.py
idem_azure_auto/pop_create/azure/api_reference.py
idem_azure_auto/pop_create/azure/api_spec.py
idem_azure_auto/pop_create/azure/init.py
idem_azure_auto/pop_create/azure/plugin.py
idem_azure_auto/pop_create/azure/resource.py
idem_azure_auto/pop_create/azure/rest.py
idem_azure_auto/pop_create/azure/template.py
idem_azure_auto/reconcile/pending/azure.py
idem_azure_auto/states/azure/init.py
idem_azure_auto/states/azure/authorization/role_assignments.py
idem_azure_auto/states/azure/authorization/role_definitions.py
idem_azure_auto/states/azure/compute/virtual_machines.py
idem_azure_auto/states/azure/management_groups/management_groups.py
idem_azure_auto/states/azure/network/network_interfaces.py
idem_azure_auto/states/azure/network/network_security_groups.py
idem_azure_auto/states/azure/network/route_tables.py
idem_azure_auto/states/azure/network/subnets.py
idem_azure_auto/states/azure/network/virtual_networks.py
idem_azure_auto/states/azure/policy/policy_assignments.py
idem_azure_auto/states/azure/policy/policy_definitions.py
idem_azure_auto/states/azure/resource_management/resource_groups.py
idem_azure_auto/states/azure/subscription/attach_subscriptions.py
idem_azure_auto/states/azure/subscription/subscriptions.py
idem_azure_auto/tool/azure/container.py
idem_azure_auto/tool/azure/request.py
idem_azure_auto/tool/azure/test_state_utils.py
idem_azure_auto/tool/azure/uri.py
idem_azure_auto-0.2.6.dist-info/LICENSE
idem_azure_auto-0.2.6.dist-info/METADATA
idem_azure_auto-0.2.6.dist-info/WHEEL
idem_azure_auto-0.2.6.dist-info/top_level.txt
idem_azure_auto-0.2.6.dist-info/RECORD
