Metadata-Version: 2.1
Name: idem-azure-auto
Version: 0.2.6
Summary: UNKNOWN
Home-page: https://gitlab.com/vmware/idem/idem-azure-auto
Author: Yingzhi Hao
Author-email: hyingzhi@vmware.com
License: UNKNOWN
Platform: UNKNOWN
Classifier: Environment :: Console
Classifier: Intended Audience :: Developers
Classifier: Intended Audience :: Information Technology
Classifier: Intended Audience :: System Administrators
Classifier: Operating System :: OS Independent
Classifier: Programming Language :: Python
Classifier: Programming Language :: Python :: 3.7
Classifier: Programming Language :: Python :: 3.8
Classifier: Programming Language :: Python :: 3.9
Classifier: Programming Language :: Python :: 3.10
Classifier: Development Status :: 5 - Production/Stable
Requires-Python: >=3.7
License-File: LICENSE
Requires-Dist: dict-toolbox (>=2.2.0)
Requires-Dist: idem (>=20.1.0)
Requires-Dist: idem-aiohttp (>=3.0.0)
Requires-Dist: validators
Provides-Extra: autogen
Requires-Dist: bs4 ; extra == 'autogen'
Requires-Dist: lxml ; extra == 'autogen'
Requires-Dist: pop-create-idem (>=2.0.1) ; extra == 'autogen'
Requires-Dist: requests ; extra == 'autogen'
Requires-Dist: tqdm ; extra == 'autogen'
Requires-Dist: validators ; extra == 'autogen'
Provides-Extra: full
Requires-Dist: pop-create-idem (>=2.0.1) ; extra == 'full'
Requires-Dist: validators ; extra == 'full'
Requires-Dist: lxml ; extra == 'full'
Requires-Dist: bs4 ; extra == 'full'
Requires-Dist: tqdm ; extra == 'full'
Requires-Dist: requests ; extra == 'full'
